PercentRD/Percent.py
PercentRD/__init__.py
PercentRD-0.1.dist-info/METADATA
PercentRD-0.1.dist-info/WHEEL
PercentRD-0.1.dist-info/top_level.txt
PercentRD-0.1.dist-info/RECORD
