Metadata-Version: 2.1
Name: PercentRD
Version: 0.1
Summary: Percent Random Return
Home-page: https://github.com/AODevStorm
Author: DevStorm
Author-email: storm@stormdev.club
License: UNKNOWN
Platform: UNKNOWN
Classifier: Programming Language :: Python :: 3
Classifier: License :: OSI Approved :: MIT License
